{
	"ImportPath": "github.com/iansmith/movienight",
	"GoVersion": "go1.4.2",
	"Packages": [
		"./server/..."
	],
	"Deps": [
		{
			"ImportPath": "github.com/coocood/qbs",
			"Comment": "0.2.1-28-gfd3760a",
			"Rev": "fd3760a61793dd4333e0c29ce9856cff9e4a7323"
		},
		{
			"ImportPath": "github.com/garyburd/go-oauth/oauth",
			"Rev": "3131beb69b81ff119923bdefbf029318f1f53794"
		},
		{
			"ImportPath": "github.com/gopherjs/gopherjs/js",
			"Rev": "272350f0ce06e6a42d3fd69db433a8b2edb651c3"
		},
		{
			"ImportPath": "github.com/gopherjs/gopherjs/nosync",
			"Rev": "272350f0ce06e6a42d3fd69db433a8b2edb651c3"
		},
		{
			"ImportPath": "github.com/gopherjs/jquery",
			"Rev": "fb45a6e6cc96d16a42442777c841ff86a3ce11a7"
		},
		{
			"ImportPath": "github.com/seven5/seven5",
			"Comment": "cure.2-2-g324deb5",
			"Rev": "324deb5f5428fac63892b16a6fd63bd783787e06"
		}
	]
}
